detro/__init__.py
detro/configs.py
detro/debug.py
detro/datasets/__init__.py
detro/datasets/det_dataset.py
detro/datasets/shapedet_dataset.py
detro/networks/__init__.py
detro/networks/losslib.py
detro/networks/backbones/__init__.py
detro/networks/backbones/resnet_backbone.py
detro/networks/backbones/efficientnet/__init__.py
detro/networks/backbones/efficientnet/backbone.py
detro/networks/backbones/efficientnet/rectifier.py
detro/networks/backbones/efficientnet/efficientdet/__init__.py
detro/networks/backbones/efficientnet/efficientdet/config.py
detro/networks/backbones/efficientnet/efficientdet/dataset.py
detro/networks/backbones/efficientnet/efficientdet/loss.py
detro/networks/backbones/efficientnet/efficientdet/model.py
detro/networks/backbones/efficientnet/efficientdet/utils.py
detro/networks/backbones/efficientnet/efficientnet/__init__.py
detro/networks/backbones/efficientnet/efficientnet/model.py
detro/networks/backbones/efficientnet/efficientnet/utils.py
detro/networks/backbones/efficientnet/efficientnet/utils_extra.py
detro/networks/components/__init__.py
detro/networks/components/components.py
detro/networks/components/layers.py
detro/networks/components/resnet.py
detro/networks/heads/__init__.py
detro/networks/models/__init__.py
detro/networks/models/efficientquadnet/__init__.py
detro/networks/models/efficientquadnet/backbone.py
detro/networks/models/efficientquadnet/efficientdet/__init__.py
detro/networks/models/efficientquadnet/efficientdet/config.py
detro/networks/models/efficientquadnet/efficientdet/dataset.py
detro/networks/models/efficientquadnet/efficientdet/loss.py
detro/networks/models/efficientquadnet/efficientdet/model.py
detro/networks/models/efficientquadnet/efficientdet/utils.py
detro/networks/models/efficientquadnet/efficientnet/__init__.py
detro/networks/models/efficientquadnet/efficientnet/model.py
detro/networks/models/efficientquadnet/efficientnet/utils.py
detro/networks/models/efficientquadnet/efficientnet/utils_extra.py
detro-0.0.0.2.dist-info/LICENSE
detro-0.0.0.2.dist-info/METADATA
detro-0.0.0.2.dist-info/WHEEL
detro-0.0.0.2.dist-info/entry_points.txt
detro-0.0.0.2.dist-info/top_level.txt
detro-0.0.0.2.dist-info/RECORD
