Metadata-Version: 2.1
Name: detro
Version: 0.0.0.2
Summary: A simple package for object detection.
Home-page: https://github.com/Peiiii/detro
Author: Wang Pei
Author-email: 1535376447@qq.com
License: UNKNOWN
Platform: UNKNOWN
Classifier: Programming Language :: Python :: 3
Classifier: License :: OSI Approved :: MIT License
Classifier: Operating System :: OS Independent
Requires-Python: >=3.0
Requires-Dist: jinja2
